<?xml version="1.0" ?>
<Intrinsic_parameters>
    <fc>2246.549237431 2246.529763337</fc>
    <cc>1004.479109675 1018.326399999</cc>
</Intrinsic_parameters>
<Distortions>
    <kc>-0.091510046 0.091217604 -0.000551529 -0.000802970 0.003748776</kc>
</Distortions>
<Error>
    <Repro_Norm_error>0.021080</Repro_Norm_error>
    <Repro_error>0.014331 0.015460</Repro_error>
    <fc_error>0.293806 0.301816</fc_error>
    <cc_error>0.180367 0.214137</cc_error>
    <kc_error>0.000131 0.000309 0.000022 0.000020</kc_error>
</Error>
<Image_RT size="23">
    <n0>
        <R>0.034462 0.012030 -0.087425</R>
        <T>-409.334268 -400.040406 1086.911279</T>
        <Repro_Norm_error>0.021771</Repro_Norm_error>
    </n0>
    <n1>
        <R>-0.335193 0.040479 -0.022946</R>
        <T>-443.222060 165.561276 1157.625803</T>
        <Repro_Norm_error>0.022825</Repro_Norm_error>
    </n1>
    <n2>
        <R>0.043433 0.009487 -0.020277</R>
        <T>47.710771 -455.200462 1073.730591</T>
        <Repro_Norm_error>0.023981</Repro_Norm_error>
    </n2>
    <n3>
        <R>-0.205012 0.013857 0.024212</R>
        <T>53.040119 132.466777 1108.456754</T>
        <Repro_Norm_error>0.024613</Repro_Norm_error>
    </n3>
    <n4>
        <R>-0.311293 0.024693 0.082112</R>
        <T>-150.171040 -243.295783 1262.923208</T>
        <Repro_Norm_error>0.019603</Repro_Norm_error>
    </n4>
    <n5>
        <R>-0.295338 0.125822 0.709994</R>
        <T>-24.690598 -314.466363 1285.476345</T>
        <Repro_Norm_error>0.020241</Repro_Norm_error>
    </n5>
    <n6>
        <R>-0.249087 0.240498 1.431741</R>
        <T>156.045681 -313.623024 1283.398433</T>
        <Repro_Norm_error>0.021863</Repro_Norm_error>
    </n6>
    <n7>
        <R>-0.093075 0.426472 2.587853</R>
        <T>308.911688 -64.999494 1199.921500</T>
        <Repro_Norm_error>0.018429</Repro_Norm_error>
    </n7>
    <n8>
        <R>-0.148974 -0.397128 -2.457191</R>
        <T>134.628096 29.580781 1171.628797</T>
        <Repro_Norm_error>0.019137</Repro_Norm_error>
    </n8>
    <n9>
        <R>-0.255429 -0.245481 -1.558514</R>
        <T>-130.852184 84.444668 1156.276643</T>
        <Repro_Norm_error>0.018744</Repro_Norm_error>
    </n9>
    <n10>
        <R>-0.287276 -0.169165 -1.091535</R>
        <T>-241.000733 -80.891206 1211.795745</T>
        <Repro_Norm_error>0.018753</Repro_Norm_error>
    </n10>
    <n11>
        <R>-0.508685 0.001718 -0.031658</R>
        <T>-172.792255 -10.329944 1319.845320</T>
        <Repro_Norm_error>0.023721</Repro_Norm_error>
    </n11>
    <n12>
        <R>-0.462312 0.270312 0.983739</R>
        <T>75.941904 -66.371853 1349.664276</T>
        <Repro_Norm_error>0.021666</Repro_Norm_error>
    </n12>
    <n13>
        <R>-0.344641 0.490480 1.822068</R>
        <T>91.657733 -0.380953 1314.125646</T>
        <Repro_Norm_error>0.018418</Repro_Norm_error>
    </n13>
    <n14>
        <R>-0.188212 -0.683749 -2.574157</R>
        <T>40.881986 363.652356 1107.054897</T>
        <Repro_Norm_error>0.017245</Repro_Norm_error>
    </n14>
    <n15>
        <R>-0.478682 -0.232160 -0.896770</R>
        <T>-271.705392 32.972468 1297.630319</T>
        <Repro_Norm_error>0.017779</Repro_Norm_error>
    </n15>
    <n16>
        <R>-0.327941 0.181365 -0.827795</R>
        <T>-233.376424 81.520562 1266.062797</T>
        <Repro_Norm_error>0.022082</Repro_Norm_error>
    </n16>
    <n17>
        <R>-0.121859 0.355997 0.610468</R>
        <T>-226.230107 -189.472694 1329.442219</T>
        <Repro_Norm_error>0.019525</Repro_Norm_error>
    </n17>
    <n18>
        <R>0.227255 0.412298 2.261561</R>
        <T>116.556259 38.635465 1167.235896</T>
        <Repro_Norm_error>0.020708</Repro_Norm_error>
    </n18>
    <n19>
        <R>-0.459455 -0.158404 -2.463381</R>
        <T>-58.728329 102.611122 1207.535471</T>
        <Repro_Norm_error>0.016026</Repro_Norm_error>
    </n19>
    <n20>
        <R>-0.131102 -0.394053 2.133445</R>
        <T>297.355151 -78.271289 1260.922376</T>
        <Repro_Norm_error>0.027919</Repro_Norm_error>
    </n20>
    <n21>
        <R>0.406844 0.077366 -1.977168</R>
        <T>-117.247288 199.689878 1225.720922</T>
        <Repro_Norm_error>0.017046</Repro_Norm_error>
    </n21>
    <n22>
        <R>0.233349 -0.262317 0.071881</R>
        <T>-178.100400 -35.839452 1148.092783</T>
        <Repro_Norm_error>0.027471</Repro_Norm_error>
    </n22>
</Image_RT>
